countdown/__init__.py
countdown/app.py
countdown/countdown.py
countdown_timer-0.0.2.dist-info/LICENSE
countdown_timer-0.0.2.dist-info/METADATA
countdown_timer-0.0.2.dist-info/WHEEL
countdown_timer-0.0.2.dist-info/top_level.txt
countdown_timer-0.0.2.dist-info/RECORD
