Metadata-Version: 2.1
Name: countdown-timer
Version: 0.0.2
Summary: A simple countdown
Home-page: https://gitea.com/chopin42/countdown
Author: Snowcode
License: UNKNOWN
Platform: UNKNOWN
Classifier: Programming Language :: Python :: 3
Classifier: License :: OSI Approved :: MIT License
Classifier: Operating System :: OS Independent
Requires-Python: >=3.6
